django_old_new_history/__init__.py
django_old_new_history/admin.py
django_old_new_history/templates/django_customize_history/object_history.html
django_old_new_history/templates/django_old_new_history/object_history.html
django_old_new_history-1.0.3.dist-info/LICENSE
django_old_new_history-1.0.3.dist-info/METADATA
django_old_new_history-1.0.3.dist-info/WHEEL
django_old_new_history-1.0.3.dist-info/top_level.txt
django_old_new_history-1.0.3.dist-info/RECORD
